<?xml version="1.0" encoding="UTF-8" ?>
<XMLDB PATH="blocks/mailchimp/db" VERSION="20130307" COMMENT="XMLDB file for Moodle blocks/mailchimp"
    xmlns:xsi="http://www.w3.org/2001/XMLSchema-instance"
    xsi:noNamespaceSchemaLocation="../../../lib/xmldb/xmldb.xsd"
>
  <TABLES>
    <TABLE NAME="block_mailchimp_users" COMMENT="block_mailchimp_users table retrofitted from MySQL">
      <FIELDS>
        <FIELD NAME="id" TYPE="int" LENGTH="9" NOTNULL="true" SEQUENCE="true"/>
        <FIELD NAME="userid" TYPE="int" LENGTH="9" NOTNULL="true" SEQUENCE="false"/>
        <FIELD NAME="email" TYPE="char" LENGTH="250" NOTNULL="true" SEQUENCE="false"/>
        <FIELD NAME="registered" TYPE="int" LENGTH="2" NOTNULL="true" SEQUENCE="false"/>
        <FIELD NAME="timecreated" TYPE="int" LENGTH="11" NOTNULL="true" SEQUENCE="false"/>
        <FIELD NAME="timemodified" TYPE="int" LENGTH="11" NOTNULL="true" SEQUENCE="false"/>
      </FIELDS>
      <KEYS>
        <KEY NAME="primary" TYPE="primary" FIELDS="id"/>
      </KEYS>
      <INDEXES>
        <INDEX NAME="userid" UNIQUE="true" FIELDS="userid"/>
      </INDEXES>
    </TABLE>
  </TABLES>
</XMLDB>